hydrogenpay_python/__init__.py
hydrogenpay_python/banktransfer.py
hydrogenpay_python/base.py
hydrogenpay_python/card.py
hydrogenpay_python/confirmpayment.py
hydrogenpay_python/exceptions.py
hydrogenpay_python/hydrogenpay.py
hydrogenpay_python/misc.py
hydrogenpay_python/payment.py
hydrogenpay_python/paymentservice.py
hydrogenpay_python/transfer.py
tests/__init__.py
tests/test_aggregate_billing_information.py
tests/test_card_purchase_confirm_status.py
tests/test_confirm_payment.py
tests/test_generate_client_key.py
tests/test_initiate_bank_transfer.py
tests/test_initiate_payment.py
tests/test_purchase.py
tests/test_resend_otp.py
tests/test_simulate_bank_transfer.py
tests/test_validate_3dsecure.py
tests/test_validate_otp.py
hydrogenpay_python-1.0.4.dist-info/LICENSE
hydrogenpay_python-1.0.4.dist-info/METADATA
hydrogenpay_python-1.0.4.dist-info/WHEEL
hydrogenpay_python-1.0.4.dist-info/top_level.txt
hydrogenpay_python-1.0.4.dist-info/RECORD
