Metadata-Version: 2.1
Name: hydrogenpay_python
Version: 1.0.4
Summary: Python library for Hydrogen to process payments through card transactions and account transfers, ensuring faster delivery of goods and services.
Home-page: https://github.com/HydrogenAfrica/python-sdk
Author: Hydrogen
Author-email: support@hydrogenpay.com
License: MIT
Classifier: Programming Language :: Python :: 2
Classifier: Programming Language :: Python :: 2.7
Classifier: Programming Language :: Python :: 3
Classifier: Programming Language :: Python :: 3.5
Classifier: Programming Language :: Python :: 3.6
Classifier: Programming Language :: Python :: 3.7
Classifier: Programming Language :: Python :: 3.8
Classifier: License :: OSI Approved :: MIT License
Classifier: Operating System :: OS Independent
Requires-Python: >=2.7, <4
License-File: LICENSE
Requires-Dist: pycryptodome
Requires-Dist: requests
